critiqypy/__init__.py
critiqypy/main.py
critiqypy-0.1.0.dist-info/LICENSE
critiqypy-0.1.0.dist-info/METADATA
critiqypy-0.1.0.dist-info/WHEEL
critiqypy-0.1.0.dist-info/entry_points.txt
critiqypy-0.1.0.dist-info/RECORD
