Metadata-Version: 2.1
Name: critiqypy
Version: 0.1.0
Summary: Critiqypy is a File Categorizer Tool. It allows you to quickly view all files in a folder, and categorize them into categories you have defined. A straightforward example is looking through photos quickly, selecting some for printing, while discarding others.
Home-page: https://github.com/WetenSchaap/Critiqypy
Author: Piet J.M. Swinkels
Requires-Python: >=3.10,<4.0
Classifier: Programming Language :: Python :: 3
Classifier: Programming Language :: Python :: 3.10
Classifier: Programming Language :: Python :: 3.11
Requires-Dist: filetype (>=1.2.0,<2.0.0)
Requires-Dist: pillow (>=10.2.0,<11.0.0)
Requires-Dist: pysimplegui (>=4.60.5,<5.0.0)
Requires-Dist: python-vlc (>=3.0.20123,<4.0.0)
Project-URL: Repository, https://github.com/WetenSchaap/Critiqypy
